twitter_activity/activity_manager/activity_extractor.py
twitter_activity/webhook_manager/twitter_webhook_manager.py
twitter_activity-0.0.1.dist-info/LICENSE
twitter_activity-0.0.1.dist-info/METADATA
twitter_activity-0.0.1.dist-info/WHEEL
twitter_activity-0.0.1.dist-info/top_level.txt
twitter_activity-0.0.1.dist-info/RECORD
