Metadata-Version: 2.1
Name: twitter-activity
Version: 0.0.1
Summary: This library is to help you work with web-hook, Classify twitter account activities
Home-page: https://github.com/Samer92/twitter_activity
Author: sammer sallam
Author-email: samersallam92@gmail.com
License: UNKNOWN
Platform: UNKNOWN
Classifier: Programming Language :: Python :: 3
Classifier: License :: OSI Approved :: MIT License
Classifier: Operating System :: OS Independent
Requires-Python: >=3.6
Requires-Dist: certifi (==2020.4.5.2)
Requires-Dist: chardet (==3.0.4)
Requires-Dist: idna (==2.9)
Requires-Dist: oauthlib (==3.1.0)
Requires-Dist: PySocks (==1.7.1)
Requires-Dist: requests (==2.24.0)
Requires-Dist: requests-oauthlib (==1.3.0)
Requires-Dist: six (==1.15.0)
Requires-Dist: tweepy (==3.8.0)
Requires-Dist: urllib3 (==1.25.9)
